python_gpapi2-0.1.2.dist-info/METADATA
python_gpapi2-0.1.2.dist-info/WHEEL
python_gpapi2-0.1.2.dist-info/license_files/LICENSE-APACHE
python_gpapi2-0.1.2.dist-info/license_files/LICENSE-MIT
gpapi2/__init__.py
gpapi2/__init__.pyi
gpapi2/py.typed
gpapi2/gpapi2.pyd
python_gpapi2-0.1.2.dist-info/RECORD
